[[{"location":"C:\\Users\\AbuSiddiqi\\.m2\\repository\\org\\springframework\\spring-web\\5.1.2.RELEASE\\spring-web-5.1.2.RELEASE.jar","type":"JAR","hints":{}},"ABSENT"],[{"location":"C:\\ServiceMeshTraining\\Student\\StudentApp","type":"PROJECT","hints":{"PROJECT_NAME":"StudentApp"}},"com.student:StudentApp:0.0.1"],[{"location":"C:\\ServiceMeshTraining\\School\\SchoolAPI","type":"PROJECT","hints":{"PROJECT_NAME":"SchoolAPI"}},"com.school:SchoolAPI:0.0.1"],[{"location":"C:\\ServiceMeshTraining\\Student\\StudentAPI","type":"PROJECT","hints":{"PROJECT_NAME":"StudentAPI"}},"com.student:StudentAPI:0.0.1"],[{"location":"C:\\Users\\AbuSiddiqi\\.m2\\repository\\org\\springframework\\boot\\spring-boot\\2.1.0.RELEASE\\spring-boot-2.1.0.RELEASE.jar","type":"JAR","hints":{}},"ABSENT"],[{"location":"C:\\Program Files\\Java\\jdk1.8.0_181","type":"JRE","hints":{"EXECUTION_ENVIRONMENT":"JavaSE-1.8"}},"jre:jre:1.8.0"],[{"location":"C:\\ServiceMeshTraining\\School\\SchoolApp","type":"PROJECT","hints":{"PROJECT_NAME":"SchoolApp"}},"com.school:SchoolApp:0.0.1"]]